New_AI_smvec/__init__.py
New_AI_smvec/chat bot for pizza .py
New_AI_smvec/faceattendance.py
New_AI_smvec/m-wallet.py
New_AI_smvec/rating.py
New_AI_smvec/shopping.py
New_AI_smvec/timetbale.py
New_AI_smvec/tourist.py
new_ai_smvec-0.1.dist-info/METADATA
new_ai_smvec-0.1.dist-info/WHEEL
new_ai_smvec-0.1.dist-info/top_level.txt
new_ai_smvec-0.1.dist-info/RECORD
